orsj_submit/__init__.py
orsj_submit/__main__.py
orsj_submit/orsj/__init__.py
orsj_submit/orsj/static/content/bootstrap.css
orsj_submit/orsj/static/content/bootstrap.min.css
orsj_submit/orsj/static/content/navbar-fixed-side.css
orsj_submit/orsj/static/content/site.css
orsj_submit/orsj/static/fonts/glyphicons-halflings-regular.eot
orsj_submit/orsj/static/fonts/glyphicons-halflings-regular.svg
orsj_submit/orsj/static/fonts/glyphicons-halflings-regular.ttf
orsj_submit/orsj/static/fonts/glyphicons-halflings-regular.woff
orsj_submit/orsj/static/pdf/empty.pdf
orsj_submit/orsj/static/scripts/_references.js
orsj_submit/orsj/static/scripts/bootstrap.js
orsj_submit/orsj/static/scripts/bootstrap.min.js
orsj_submit/orsj/static/scripts/jquery-1.10.2.intellisense.js
orsj_submit/orsj/static/scripts/jquery-1.10.2.js
orsj_submit/orsj/static/scripts/jquery-1.10.2.min.js
orsj_submit/orsj/static/scripts/jquery-1.10.2.min.map
orsj_submit/orsj/static/scripts/jquery.validate-vsdoc.js
orsj_submit/orsj/static/scripts/jquery.validate.js
orsj_submit/orsj/static/scripts/jquery.validate.min.js
orsj_submit/orsj/static/scripts/jquery.validate.unobtrusive.js
orsj_submit/orsj/static/scripts/jquery.validate.unobtrusive.min.js
orsj_submit/orsj/static/scripts/modernizr-2.6.2.js
orsj_submit/orsj/static/scripts/respond.js
orsj_submit/orsj/static/scripts/respond.min.js
orsj_submit/orsj/templates/account.jade
orsj_submit/orsj/templates/articles.jade
orsj_submit/orsj/templates/assign.jade
orsj_submit/orsj/templates/check.jade
orsj_submit/orsj/templates/del_user.jade
orsj_submit/orsj/templates/desc.jade
orsj_submit/orsj/templates/forget.jade
orsj_submit/orsj/templates/index.jade
orsj_submit/orsj/templates/layout.jade
orsj_submit/orsj/templates/login.jade
orsj_submit/orsj/templates/message.jade
orsj_submit/orsj/templates/signup.jade
orsj_submit/orsj/templates/submit.jade
orsj_submit/orsj/templates/summary.jade
orsj_submit/orsj/util.py
orsj_submit/orsj/views.py
orsj_submit/setting.yml
orsj_submit/start_cmd
orsj_submit-0.2.1.dist-info/LICENSE
orsj_submit-0.2.1.dist-info/METADATA
orsj_submit-0.2.1.dist-info/WHEEL
orsj_submit-0.2.1.dist-info/entry_points.txt
orsj_submit-0.2.1.dist-info/RECORD
