Metadata-Version: 2.1
Name: orsj-submit
Version: 0.2.1
Summary: Web application of 'submitting papers' in ORSJ.
Home-page: https://github.com/SaitoTsutomu/orsj-submit
License: Apache-2.0
Author: SaitoTsutomu
Author-email: tsutomu7@hotmail.co.jp
Requires-Python: >=3.11,<4.0
Classifier: Development Status :: 1 - Planning
Classifier: License :: OSI Approved :: Apache Software License
Classifier: Programming Language :: Python
Classifier: Programming Language :: Python :: 3
Classifier: Programming Language :: Python :: 3.11
Classifier: Topic :: Scientific/Engineering
Classifier: Topic :: Software Development
